hermes/__init__.py
hermes/__main__.py
hermes/endpoints.py
hermes/stroke_regressor.py
hermes_se2021-1.0.1.dist-info/LICENSE
hermes_se2021-1.0.1.dist-info/WHEEL
hermes_se2021-1.0.1.dist-info/METADATA
hermes_se2021-1.0.1.dist-info/RECORD
